{
  "metadata": {
    "fetched_at": "2026-06-09T10:53:11.853548",
    "year": 2026,
    "week": 23,
    "total_localities": 1779
  },
  "summary": {
    "diseaseOutbreaks": [
      {
        "locality": {
          "no": 38857,
          "name": "Vannfjorden",
          "isOnLand": false
        },
        "disease": {
          "name": "INFEKSIOES_LAKSEANEMI",
          "subType": null,
          "status": "SUSPECTED"
        }
      },
      {
        "locality": {
          "no": 11688,
          "name": "Portevika",
          "isOnLand": false
        },
        "disease": {
          "name": "PANKREASSYKDOM",
          "subType": "SAV3",
          "status": "SUSPECTED"
        }
      }
    ],
    "diseaseStatistics": [
      {
        "name": "PANKREASSYKDOM",
        "count": 40
      },
      {
        "name": "FRANCISELLOSE",
        "count": 2
      },
      {
        "name": "INFEKSIOES_LAKSEANEMI",
        "count": 11
      },
      {
        "name": "BAKTERIELL_NYRESYKE",
        "count": 2
      }
    ],
    "annualDiseaseStatistics": {
      "isFiltered": true,
      "diseaseStatistics": [
        {
          "name": "BAKTERIELL_NYRESYKE",
          "count": 2
        },
        {
          "name": "FRANCISELLOSE",
          "count": 1
        },
        {
          "name": "INFEKSIOES_LAKSEANEMI",
          "count": 7
        },
        {
          "name": "PANKREASSYKDOM",
          "count": 27
        }
      ],
      "filteredDiseaseStatistics": [
        {
          "name": "BAKTERIELL_NYRESYKE",
          "count": 2
        },
        {
          "name": "FRANCISELLOSE",
          "count": 1
        },
        {
          "name": "INFEKSIOES_LAKSEANEMI",
          "count": 7
        },
        {
          "name": "PANKREASSYKDOM",
          "count": 24
        }
      ],
      "weeklyDiseaseStatistics": {
        "1": [],
        "2": [
          {
            "name": "PANKREASSYKDOM",
            "count": 2
          }
        ],
        "3": [
          {
            "name": "PANKREASSYKDOM",
            "count": 3
          }
        ],
        "4": [
          {
            "name": "BAKTERIELL_NYRESYKE",
            "count": 1
          },
          {
            "name": "PANKREASSYKDOM",
            "count": 1
          }
        ],
        "5": [
          {
            "name": "PANKREASSYKDOM",
            "count": 3
          }
        ],
        "6": [
          {
            "name": "PANKREASSYKDOM",
            "count": 3
          }
        ],
        "7": [
          {
            "name": "FRANCISELLOSE",
            "count": 1
          },
          {
            "name": "PANKREASSYKDOM",
            "count": 1
          }
        ],
        "8": [
          {
            "name": "INFEKSIOES_LAKSEANEMI",
            "count": 1
          },
          {
            "name": "PANKREASSYKDOM",
            "count": 1
          }
        ],
        "9": [
          {
            "name": "PANKREASSYKDOM",
            "count": 2
          }
        ],
        "10": [],
        "11": [
          {
            "name": "PANKREASSYKDOM",
            "count": 4
          }
        ],
        "12": [
          {
            "name": "INFEKSIOES_LAKSEANEMI",
            "count": 1
          }
        ],
        "13": [
          {
            "name": "BAKTERIELL_NYRESYKE",
            "count": 1
          }
        ],
        "14": [],
        "15": [],
        "16": [
          {
            "name": "PANKREASSYKDOM",
            "count": 1
          }
        ],
        "17": [
          {
            "name": "INFEKSIOES_LAKSEANEMI",
            "count": 1
          }
        ],
        "18": [],
        "19": [],
        "20": [
          {
            "name": "INFEKSIOES_LAKSEANEMI",
            "count": 2
          },
          {
            "name": "PANKREASSYKDOM",
            "count": 2
          }
        ],
        "21": [],
        "22": [
          {
            "name": "INFEKSIOES_LAKSEANEMI",
            "count": 1
          }
        ],
        "23": [
          {
            "name": "INFEKSIOES_LAKSEANEMI",
            "count": 1
          },
          {
            "name": "PANKREASSYKDOM",
            "count": 1
          }
        ],
        "24": [],
        "25": [],
        "26": [],
        "27": [],
        "28": [],
        "29": [],
        "30": [],
        "31": [],
        "32": [],
        "33": [],
        "34": [],
        "35": [],
        "36": [],
        "37": [],
        "38": [],
        "39": [],
        "40": [],
        "41": [],
        "42": [],
        "43": [],
        "44": [],
        "45": [],
        "46": [],
        "47": [],
        "48": [],
        "49": [],
        "50": [],
        "51": [],
        "52": [],
        "53": []
      }
    },
    "liceStatistics": {
      "aboveThreshold": {
        "count": 2,
        "percentage": 0.5714285714285714
      },
      "belowThreshold": {
        "count": 348,
        "percentage": 99.42857142857143
      },
      "belowMinimumThreshold": {
        "count": 290,
        "percentage": 82.85714285714286
      }
    },
    "annualLiceStatistics": {
      "isFiltered": true,
      "liceStatistics": {
        "aboveThreshold": 118
      },
      "filteredLiceStatistics": {
        "aboveThreshold": 117
      },
      "weeklyLiceStatistics": {
        "1": {
          "aboveThreshold": 9
        },
        "2": {
          "aboveThreshold": 6
        },
        "3": {
          "aboveThreshold": 3
        },
        "4": {
          "aboveThreshold": 5
        },
        "5": {
          "aboveThreshold": 3
        },
        "6": {
          "aboveThreshold": 9
        },
        "7": {
          "aboveThreshold": 10
        },
        "8": {
          "aboveThreshold": 4
        },
        "9": {
          "aboveThreshold": 4
        },
        "10": {
          "aboveThreshold": 2
        },
        "11": {
          "aboveThreshold": 4
        },
        "12": {
          "aboveThreshold": 6
        },
        "13": {
          "aboveThreshold": 4
        },
        "14": {
          "aboveThreshold": 3
        },
        "15": {
          "aboveThreshold": 3
        },
        "16": {
          "aboveThreshold": 11
        },
        "17": {
          "aboveThreshold": 4
        },
        "18": {
          "aboveThreshold": 6
        },
        "19": {
          "aboveThreshold": 4
        },
        "20": {
          "aboveThreshold": 3
        },
        "21": {
          "aboveThreshold": 9
        },
        "22": {
          "aboveThreshold": 3
        },
        "23": {
          "aboveThreshold": 2
        },
        "24": {
          "aboveThreshold": 0
        },
        "25": {
          "aboveThreshold": null
        },
        "26": {
          "aboveThreshold": null
        },
        "27": {
          "aboveThreshold": null
        },
        "28": {
          "aboveThreshold": null
        },
        "29": {
          "aboveThreshold": null
        },
        "30": {
          "aboveThreshold": null
        },
        "31": {
          "aboveThreshold": null
        },
        "32": {
          "aboveThreshold": null
        },
        "33": {
          "aboveThreshold": null
        },
        "34": {
          "aboveThreshold": null
        },
        "35": {
          "aboveThreshold": null
        },
        "36": {
          "aboveThreshold": null
        },
        "37": {
          "aboveThreshold": null
        },
        "38": {
          "aboveThreshold": null
        },
        "39": {
          "aboveThreshold": null
        },
        "40": {
          "aboveThreshold": null
        },
        "41": {
          "aboveThreshold": null
        },
        "42": {
          "aboveThreshold": null
        },
        "43": {
          "aboveThreshold": null
        },
        "44": {
          "aboveThreshold": null
        },
        "45": {
          "aboveThreshold": null
        },
        "46": {
          "aboveThreshold": null
        },
        "47": {
          "aboveThreshold": null
        },
        "48": {
          "aboveThreshold": null
        },
        "49": {
          "aboveThreshold": null
        },
        "50": {
          "aboveThreshold": null
        },
        "51": {
          "aboveThreshold": null
        },
        "52": {
          "aboveThreshold": null
        },
        "53": {
          "aboveThreshold": null
        }
      }
    },
    "farmedFishEscapes": [
      {
        "locality": {
          "no": 24575,
          "name": "FARMANNSØYA",
          "isOnLand": false
        },
        "species": "Laks",
        "date": "2026-06-05T10:50:00+02:00",
        "count": null,
        "estimatedCount": "1-10",
        "estimationSource": "Breeder",
        "size": 2.8
      },
      {
        "locality": {
          "no": 14041,
          "name": "EDØYA",
          "isOnLand": false
        },
        "species": "Laks",
        "date": "2026-06-01T07:02:00+02:00",
        "count": null,
        "estimatedCount": "1-10",
        "estimationSource": "Breeder",
        "size": 1.25
      },
      {
        "locality": {
          "no": 32197,
          "name": "DRYNA",
          "isOnLand": false
        },
        "species": "Laks",
        "date": "2026-06-02T10:12:00+02:00",
        "count": null,
        "estimatedCount": "1-10",
        "estimationSource": "Breeder",
        "size": 4.856
      }
    ],
    "annualEscapeStatistics": {
      "isFiltered": false,
      "escapeStatistics": {
        "count": 29
      },
      "filteredEscapeStatistics": {
        "count": 29
      },
      "weeklyEscapeStatistics": {
        "1": {
          "count": 3
        },
        "4": {
          "count": 1
        },
        "7": {
          "count": 3
        },
        "23": {
          "count": 3
        },
        "20": {
          "count": 1
        },
        "6": {
          "count": 1
        },
        "2": {
          "count": 1
        },
        "22": {
          "count": 2
        },
        "18": {
          "count": 3
        },
        "15": {
          "count": 1
        },
        "9": {
          "count": 1
        },
        "13": {
          "count": 3
        },
        "16": {
          "count": 2
        },
        "17": {
          "count": 1
        },
        "19": {
          "count": 3
        },
        "3": {
          "count": 0
        },
        "5": {
          "count": 0
        },
        "8": {
          "count": 0
        },
        "10": {
          "count": 0
        },
        "11": {
          "count": 0
        },
        "12": {
          "count": 0
        },
        "14": {
          "count": 0
        },
        "21": {
          "count": 0
        },
        "24": {
          "count": 0
        },
        "25": {
          "count": null
        },
        "26": {
          "count": null
        },
        "27": {
          "count": null
        },
        "28": {
          "count": null
        },
        "29": {
          "count": null
        },
        "30": {
          "count": null
        },
        "31": {
          "count": null
        },
        "32": {
          "count": null
        },
        "33": {
          "count": null
        },
        "34": {
          "count": null
        },
        "35": {
          "count": null
        },
        "36": {
          "count": null
        },
        "37": {
          "count": null
        },
        "38": {
          "count": null
        },
        "39": {
          "count": null
        },
        "40": {
          "count": null
        },
        "41": {
          "count": null
        },
        "42": {
          "count": null
        },
        "43": {
          "count": null
        },
        "44": {
          "count": null
        },
        "45": {
          "count": null
        },
        "46": {
          "count": null
        },
        "47": {
          "count": null
        },
        "48": {
          "count": null
        },
        "49": {
          "count": null
        },
        "50": {
          "count": null
        },
        "51": {
          "count": null
        },
        "52": {
          "count": null
        },
        "53": {
          "count": null
        }
      }
    }
  }
}